test/__init__.py
test/test_apod.py
test/test_astrobin.py
test/test_bing.py
test/test_epod.py
test/test_nasa.py
test/test_national_geographic.py
test/test_reddit.py
test/test_tetras.py
test/test_the_guardian.py
test/test_the_telegraph.py
test/test_website.py
test/test_wikipedia.py
test/test_windows_spotlight.py
wallme/__init__.py
wallme/exceptions.py
wallme/gui.py
wallme/log.py
wallme/main.py
wallme/utils.py
wallme/managers/__init__.py
wallme/managers/linux.py
wallme/managers/macos.py
wallme/managers/manager.py
wallme/managers/managerfactory.py
wallme/managers/windows.py
wallme/websites/__init__.py
wallme/websites/apod.py
wallme/websites/astrobin.py
wallme/websites/bing.py
wallme/websites/epod.py
wallme/websites/nasa.py
wallme/websites/national_geographic.py
wallme/websites/reddit.py
wallme/websites/tetras.py
wallme/websites/the_guardian.py
wallme/websites/the_telegraph.py
wallme/websites/website.py
wallme/websites/wikipedia.py
wallme/websites/windows_spotlight.py
wallme-1.7.dist-info/LICENSE
wallme-1.7.dist-info/METADATA
wallme-1.7.dist-info/WHEEL
wallme-1.7.dist-info/entry_points.txt
wallme-1.7.dist-info/top_level.txt
wallme-1.7.dist-info/RECORD
