Metadata-Version: 2.1
Name: wallme
Version: 1.7
Summary: Change your wallpaper every day
Home-page: https://github.com/LucBerge/wallme
Author: LucBerge
Author-email: lucas.bergeron@outlook.fr
License-File: LICENSE
Requires-Dist: requests
Requires-Dist: bs4
Requires-Dist: Pillow
